{
  "lastUpdate": "2025-12-24T08:22:17.865Z",
  "servers": [
    {
      "name": "server2",
      "status": "offline",
      "responseTime": 0,
      "lastChecked": "2025-12-24T08:22:17.861Z"
    },
    {
      "name": "server3",
      "status": "offline",
      "responseTime": 0,
      "lastChecked": "2025-12-24T08:22:17.862Z"
    },
    {
      "name": "server4",
      "status": "offline",
      "responseTime": 0,
      "lastChecked": "2025-12-24T08:22:17.862Z"
    },
    {
      "name": "server6",
      "status": "offline",
      "responseTime": 0,
      "lastChecked": "2025-12-24T08:22:17.862Z"
    },
    {
      "name": "server7",
      "status": "online",
      "responseTime": 2452,
      "lastChecked": "2025-12-24T08:20:45.244Z"
    },
    {
      "name": "server8",
      "status": "online",
      "responseTime": 3011,
      "lastChecked": "2025-12-24T08:20:45.804Z"
    },
    {
      "name": "server9",
      "status": "online",
      "responseTime": 2445,
      "lastChecked": "2025-12-24T08:20:45.238Z"
    },
    {
      "name": "server10",
      "status": "online",
      "responseTime": 2442,
      "lastChecked": "2025-12-24T08:20:45.237Z"
    }
  ]
}