{
  "lastUpdate": "2025-12-11T15:17:08.109Z",
  "servers": [
    {
      "name": "server2",
      "status": "online",
      "responseTime": 3225,
      "lastChecked": "2025-12-11T15:17:07.174Z"
    },
    {
      "name": "server3",
      "status": "online",
      "responseTime": 3466,
      "lastChecked": "2025-12-11T15:17:07.420Z"
    },
    {
      "name": "server4",
      "status": "online",
      "responseTime": 3964,
      "lastChecked": "2025-12-11T15:17:07.919Z"
    },
    {
      "name": "server6",
      "status": "online",
      "responseTime": 2725,
      "lastChecked": "2025-12-11T15:17:06.681Z"
    },
    {
      "name": "server7",
      "status": "online",
      "responseTime": 4152,
      "lastChecked": "2025-12-11T15:17:08.107Z"
    },
    {
      "name": "server8",
      "status": "online",
      "responseTime": 3291,
      "lastChecked": "2025-12-11T15:17:07.247Z"
    },
    {
      "name": "server9",
      "status": "online",
      "responseTime": 2763,
      "lastChecked": "2025-12-11T15:17:06.719Z"
    },
    {
      "name": "server10",
      "status": "online",
      "responseTime": 3242,
      "lastChecked": "2025-12-11T15:17:07.199Z"
    }
  ]
}