{
  "lastUpdate": "2025-12-04T03:14:22.218Z",
  "servers": [
    {
      "name": "server2",
      "status": "online",
      "responseTime": 2872,
      "lastChecked": "2025-12-04T03:14:11.892Z"
    },
    {
      "name": "server3",
      "status": "online",
      "responseTime": 2170,
      "lastChecked": "2025-12-04T03:14:05.676Z"
    },
    {
      "name": "server4",
      "status": "online",
      "responseTime": 3212,
      "lastChecked": "2025-12-04T03:14:06.719Z"
    },
    {
      "name": "server6",
      "status": "online",
      "responseTime": 2244,
      "lastChecked": "2025-12-04T03:14:05.750Z"
    },
    {
      "name": "server7",
      "status": "online",
      "responseTime": 2431,
      "lastChecked": "2025-12-04T03:14:05.938Z"
    },
    {
      "name": "server8",
      "status": "online",
      "responseTime": 2221,
      "lastChecked": "2025-12-04T03:14:22.216Z"
    },
    {
      "name": "server9",
      "status": "online",
      "responseTime": 2399,
      "lastChecked": "2025-12-04T03:14:05.907Z"
    },
    {
      "name": "server10",
      "status": "online",
      "responseTime": 2225,
      "lastChecked": "2025-12-04T03:14:05.733Z"
    }
  ]
}