{
  "lastUpdate": "2025-12-19T20:17:24.687Z",
  "servers": [
    {
      "name": "server2",
      "status": "offline",
      "responseTime": 0,
      "lastChecked": "2025-12-19T20:17:24.684Z"
    },
    {
      "name": "server3",
      "status": "offline",
      "responseTime": 0,
      "lastChecked": "2025-12-19T20:17:24.684Z"
    },
    {
      "name": "server4",
      "status": "offline",
      "responseTime": 0,
      "lastChecked": "2025-12-19T20:17:24.684Z"
    },
    {
      "name": "server6",
      "status": "offline",
      "responseTime": 0,
      "lastChecked": "2025-12-19T20:17:24.684Z"
    },
    {
      "name": "server7",
      "status": "online",
      "responseTime": 2203,
      "lastChecked": "2025-12-19T20:15:51.814Z"
    },
    {
      "name": "server8",
      "status": "online",
      "responseTime": 2215,
      "lastChecked": "2025-12-19T20:15:51.826Z"
    },
    {
      "name": "server9",
      "status": "online",
      "responseTime": 2045,
      "lastChecked": "2025-12-19T20:15:51.658Z"
    },
    {
      "name": "server10",
      "status": "online",
      "responseTime": 2061,
      "lastChecked": "2025-12-19T20:15:51.673Z"
    }
  ]
}