{
  "lastUpdate": "2025-12-18T17:19:45.163Z",
  "servers": [
    {
      "name": "server2",
      "status": "offline",
      "responseTime": 0,
      "lastChecked": "2025-12-18T17:19:45.160Z"
    },
    {
      "name": "server3",
      "status": "offline",
      "responseTime": 0,
      "lastChecked": "2025-12-18T17:19:45.161Z"
    },
    {
      "name": "server4",
      "status": "offline",
      "responseTime": 0,
      "lastChecked": "2025-12-18T17:19:45.161Z"
    },
    {
      "name": "server6",
      "status": "offline",
      "responseTime": 0,
      "lastChecked": "2025-12-18T17:19:45.161Z"
    },
    {
      "name": "server7",
      "status": "online",
      "responseTime": 3330,
      "lastChecked": "2025-12-18T17:18:13.413Z"
    },
    {
      "name": "server8",
      "status": "online",
      "responseTime": 2123,
      "lastChecked": "2025-12-18T17:18:12.206Z"
    },
    {
      "name": "server9",
      "status": "online",
      "responseTime": 2103,
      "lastChecked": "2025-12-18T17:18:12.187Z"
    },
    {
      "name": "server10",
      "status": "offline",
      "responseTime": 0,
      "lastChecked": "2025-12-18T17:18:26.929Z"
    }
  ]
}