{
  "lastUpdate": "2025-12-07T03:21:53.291Z",
  "servers": [
    {
      "name": "server2",
      "status": "online",
      "responseTime": 2242,
      "lastChecked": "2025-12-07T03:21:42.619Z"
    },
    {
      "name": "server3",
      "status": "online",
      "responseTime": 2063,
      "lastChecked": "2025-12-07T03:21:42.445Z"
    },
    {
      "name": "server4",
      "status": "online",
      "responseTime": 2016,
      "lastChecked": "2025-12-07T03:21:42.399Z"
    },
    {
      "name": "server6",
      "status": "online",
      "responseTime": 2187,
      "lastChecked": "2025-12-07T03:21:42.570Z"
    },
    {
      "name": "server7",
      "status": "online",
      "responseTime": 2237,
      "lastChecked": "2025-12-07T03:21:42.620Z"
    },
    {
      "name": "server8",
      "status": "online",
      "responseTime": 2226,
      "lastChecked": "2025-12-07T03:21:42.610Z"
    },
    {
      "name": "server9",
      "status": "online",
      "responseTime": 2034,
      "lastChecked": "2025-12-07T03:21:47.892Z"
    },
    {
      "name": "server10",
      "status": "online",
      "responseTime": 2037,
      "lastChecked": "2025-12-07T03:21:53.289Z"
    }
  ]
}