{
  "lastUpdate": "2025-12-19T21:14:37.869Z",
  "servers": [
    {
      "name": "server2",
      "status": "offline",
      "responseTime": 0,
      "lastChecked": "2025-12-19T21:14:37.867Z"
    },
    {
      "name": "server3",
      "status": "offline",
      "responseTime": 0,
      "lastChecked": "2025-12-19T21:14:37.867Z"
    },
    {
      "name": "server4",
      "status": "offline",
      "responseTime": 0,
      "lastChecked": "2025-12-19T21:14:37.867Z"
    },
    {
      "name": "server6",
      "status": "offline",
      "responseTime": 0,
      "lastChecked": "2025-12-19T21:14:37.867Z"
    },
    {
      "name": "server7",
      "status": "online",
      "responseTime": 2513,
      "lastChecked": "2025-12-19T21:13:05.316Z"
    },
    {
      "name": "server8",
      "status": "online",
      "responseTime": 2694,
      "lastChecked": "2025-12-19T21:13:05.499Z"
    },
    {
      "name": "server9",
      "status": "online",
      "responseTime": 2537,
      "lastChecked": "2025-12-19T21:13:05.341Z"
    },
    {
      "name": "server10",
      "status": "online",
      "responseTime": 2694,
      "lastChecked": "2025-12-19T21:13:05.498Z"
    }
  ]
}